examples/streamable_http_server.py
examples/test_streamable_http.py
smart_agent/__init__.py
smart_agent/agent.py
smart_agent/cli.py
smart_agent/process_manager.py
smart_agent/proxy_manager.py
smart_agent/tool_manager.py
smart_agent/commands/__init__.py
smart_agent/commands/chainlit.py
smart_agent/commands/chat.py
smart_agent/commands/init.py
smart_agent/commands/start.py
smart_agent/commands/status.py
smart_agent/commands/stop.py
smart_agent/config/config.yaml.example
smart_agent/config/litellm_config.yaml.example
smart_agent/core/__init__.py
smart_agent/core/agent.py
smart_agent/core/chainlit_agent.py
smart_agent/core/cli_agent.py
smart_agent/core/mcp_server.py
smart_agent/core/smooth_stream.py
smart_agent/web/__init__.py
smart_agent/web/chainlit_app.py
smart_agent/web/cleanup_handler.py
smart_agent/web/httpcore_patch.py
smart_agent/web/logging_config.py
smart_agent/web/suppress_errors.py
smart_agent/web/helpers/__init__.py
smart_agent/web/helpers/setup.py
smart_agent-0.8.8.dist-info/licenses/LICENSE
tests/__init__.py
tests/conftest.py
tests/functional/__init__.py
tests/functional/test_smart_agent_e2e.py
tests/integration/__init__.py
tests/integration/test_tool_management.py
tests/unit/__init__.py
tests/unit/test_agent.py
tests/unit/test_cli.py
tests/unit/test_config.py
smart_agent-0.8.8.dist-info/METADATA
smart_agent-0.8.8.dist-info/WHEEL
smart_agent-0.8.8.dist-info/entry_points.txt
smart_agent-0.8.8.dist-info/top_level.txt
smart_agent-0.8.8.dist-info/RECORD
