Metadata-Version: 2.4
Name: smart-agent
Version: 0.8.8
Summary: Smart AI agent with reasoning and tool use capabilities
Author-email: Don Kang <donkang34@gmail.com>
License: MIT
Project-URL: Homepage, https://github.com/ddkang1/smart-agent
Project-URL: Bug Tracker, https://github.com/ddkang1/smart-agent/issues
Classifier: Programming Language :: Python :: 3
Classifier: License :: OSI Approved :: MIT License
Classifier: Operating System :: OS Independent
Requires-Python: >=3.11
License-File: LICENSE
Requires-Dist: colorama
Requires-Dist: openai
Requires-Dist: asyncio
Requires-Dist: click
Requires-Dist: python-dotenv
Requires-Dist: pyyaml>=6.0
Requires-Dist: uv
Requires-Dist: openai-agents[litellm]==0.0.17
Requires-Dist: rich
Requires-Dist: fastmcp>=2.6.1
Requires-Dist: mcp[cli]>=1.6
Requires-Dist: backoff>=2.2.1
Requires-Dist: anyio>=3.7.0
Requires-Dist: httpcore>=1.0.9
Provides-Extra: web
Requires-Dist: chainlit; extra == "web"
Provides-Extra: monitoring
Requires-Dist: langfuse>=2.0.0; extra == "monitoring"
Provides-Extra: dev
Requires-Dist: pytest>=7.0.0; extra == "dev"
Requires-Dist: pytest-cov>=4.0.0; extra == "dev"
Requires-Dist: pytest-asyncio>=0.21.0; extra == "dev"
Requires-Dist: black>=23.0.0; extra == "dev"
Requires-Dist: flake8>=6.0.0; extra == "dev"
Requires-Dist: mypy>=1.0.0; extra == "dev"
Dynamic: license-file
